         <vf:AdresniMisto gml:id="AD.22307133">
            <ami:Kod>22307133</ami:Kod>
            <ami:CisloDomovni>1111</ami:CisloDomovni>
            <ami:CisloOrientacni>16</ami:CisloOrientacni>
            <ami:Psc>17000</ami:Psc>
            <ami:StavebniObjekt>
               <soi:Kod>22144391</soi:Kod>
            </ami:StavebniObjekt>
            <ami:Ulice>
               <uli:Kod>476137</uli:Kod>
            </ami:Ulice>
            <ami:VOKod>26065</ami:VOKod>
            <ami:PlatiOd>2017-06-29T00:00:00</ami:PlatiOd>
            <ami:IdTransakce>1929188</ami:IdTransakce>
            <ami:GlobalniIdNavrhuZmeny>1427191</ami:GlobalniIdNavrhuZmeny>
            <ami:Geometrie>
               <ami:DefinicniBod>
                  <ami:AdresniBod>
                     <gml:Point gml:id="DAM.22307133.1"
                                srsName="urn:ogc:def:crs:EPSG::5514"
                                srsDimension="2">
                        <gml:pos>-740220.34 -1041505.89</gml:pos>
                     </gml:Point>
                  </ami:AdresniBod>
               </ami:DefinicniBod>
            </ami:Geometrie>
         </vf:AdresniMisto>
