         <vf:AdresniMisto gml:id="AD.22303952">
            <ami:Kod>22303952</ami:Kod>
            <ami:CisloDomovni>839</ami:CisloDomovni>
            <ami:CisloOrientacni>49</ami:CisloOrientacni>
            <ami:Psc>17000</ami:Psc>
            <ami:StavebniObjekt>
               <soi:Kod>22141944</soi:Kod>
            </ami:StavebniObjekt>
            <ami:Ulice>
               <uli:Kod>477613</uli:Kod>
            </ami:Ulice>
            <ami:VOKod>26095</ami:VOKod>
            <ami:PlatiOd>2017-06-29T00:00:00</ami:PlatiOd>
            <ami:IdTransakce>1929170</ami:IdTransakce>
            <ami:GlobalniIdNavrhuZmeny>1427174</ami:GlobalniIdNavrhuZmeny>
            <ami:Geometrie>
               <ami:DefinicniBod>
                  <ami:AdresniBod>
                     <gml:Point gml:id="DAM.22303952.1"
                                srsName="urn:ogc:def:crs:EPSG::5514"
                                srsDimension="2">
                        <gml:pos>-742109.02 -1041574.15</gml:pos>
                     </gml:Point>
                  </ami:AdresniBod>
               </ami:DefinicniBod>
            </ami:Geometrie>
         </vf:AdresniMisto>
