         <vf:AdresniMisto gml:id="AD.28074432">
            <ami:Kod>28074432</ami:Kod>
            <ami:CisloDomovni>903</ami:CisloDomovni>
            <ami:CisloOrientacni>5</ami:CisloOrientacni>
            <ami:Psc>17000</ami:Psc>
            <ami:StavebniObjekt>
               <soi:Kod>22155007</soi:Kod>
            </ami:StavebniObjekt>
            <ami:Ulice>
               <uli:Kod>452815</uli:Kod>
            </ami:Ulice>
            <ami:VOKod>26111</ami:VOKod>
            <ami:PlatiOd>2017-06-29T00:00:00</ami:PlatiOd>
            <ami:IdTransakce>1928737</ami:IdTransakce>
            <ami:GlobalniIdNavrhuZmeny>1426734</ami:GlobalniIdNavrhuZmeny>
            <ami:Geometrie>
               <ami:DefinicniBod>
                  <ami:AdresniBod>
                     <gml:Point gml:id="DAM.28074432.1"
                                srsName="urn:ogc:def:crs:EPSG::5514"
                                srsDimension="2">
                        <gml:pos>-742747.54 -1041553.23</gml:pos>
                     </gml:Point>
                  </ami:AdresniBod>
               </ami:DefinicniBod>
            </ami:Geometrie>
         </vf:AdresniMisto>
